slxjsonrpc/__init__.py
slxjsonrpc/__init__.pyi
slxjsonrpc/jsonrpc.py
slxjsonrpc/jsonrpc.pyi
slxjsonrpc/py.typed
slxjsonrpc/schema/__init__.py
slxjsonrpc/schema/__init__.pyi
slxjsonrpc/schema/jsonrpc.py
slxjsonrpc/schema/jsonrpc.pyi
slxjsonrpc-0.9.2.data/data/info/CHANGELOG.md
slxjsonrpc-0.9.2.data/data/info/README.md
slxjsonrpc-0.9.2.dist-info/LICENSE
slxjsonrpc-0.9.2.dist-info/METADATA
slxjsonrpc-0.9.2.dist-info/WHEEL
slxjsonrpc-0.9.2.dist-info/top_level.txt
slxjsonrpc-0.9.2.dist-info/RECORD
