Metadata-Version: 2.1
Name: slxjsonrpc
Version: 0.9.2
Summary: SlxJsonRpc JsonRpc helper class, that uses pydantic.
Home-page: https://github.com/Wappsto/slxjsonrpc
Author: Seluxit A/S
Author-email: support@seluxit.com
License: Apache-2.0
Classifier: Programming Language :: Python :: 3.7
Classifier: Programming Language :: Python :: 3.8
Classifier: Programming Language :: Python :: 3.9
Classifier: Programming Language :: Python :: 3.10
Classifier: Programming Language :: Python :: 3.11
Classifier: Operating System :: OS Independent
Requires-Python: >=3.7.0
License-File: LICENSE
Requires-Dist: pydantic (>=2.1.1)
